.DS_Store
.travis.yml
AUTHORS
CONTRIBUTING.md
ChangeLog
LICENSE
README.md
paper.bib
paper.md
requirements.txt
setup.cfg
setup.py
.github/pull_request_template.md
.github/ISSUE_TEMPLATE/bug_report.md
.github/ISSUE_TEMPLATE/feature_request.md
.github/ISSUE_TEMPLATE/question-template.md
demos/manual_demo.py
demos/notebook-demo-1-nuance.ipynb
demos/notebook-demo-2-parallel.ipynb
demos/simple-demo.py
demos/images/t4_data.PNG
demos/images/t7_data.PNG
docs/Makefile
docs/conf.py
docs/demos.rst
docs/index.rst
docs/labjackcontroller.rst
docs/make.bat
docs/modules.rst
docs/overview.rst
docs/requirements.txt
docs/demos/notebook-demo-1-nuance.ipynb
docs/demos/notebook-demo-2-parallel.ipynb
docs/demos/images/t4_data.PNG
docs/demos/images/t7_data.PNG
labjackcontroller/__init__.py
labjackcontroller/labtools.py
labjackcontroller.egg-info/PKG-INFO
labjackcontroller.egg-info/SOURCES.txt
labjackcontroller.egg-info/dependency_links.txt
labjackcontroller.egg-info/not-zip-safe
labjackcontroller.egg-info/pbr.json
labjackcontroller.egg-info/requires.txt
labjackcontroller.egg-info/top_level.txt
tests/labjackcontroller_test.py