Metadata-Version: 2.1
Name: labjackcontroller
Version: 0.0.1.dev60
Summary: A helper library to control LabJack T-series devices
Home-page: http://pypi.python.org/pypi/foobar
Author: Ben Montgomery
License: MIT
Platform: UNKNOWN
Classifier: Development Status :: 4 - Beta
Classifier: Intended Audience :: Science/Research
Classifier: License :: OSI Approved :: MIT License
Classifier: Operating System :: OS Independent
Classifier: Programming Language :: Python :: 3
